gget/__init__.py
gget/__main__.py
gget/_get_remote_file.py
gget/cli.py
gget/platform/__init__.py
gget/platform/_dirent.py
gget/platform/_get_provider.py
gget/platform/_provider.py
gget/platform/_repository.py
gget/platform/github/__init__.py
gget/platform/github/_dirent.py
gget/platform/github/_provider.py
gget/platform/github/_repository.py
gget/writer/__init__.py
gget/writer/_writer.py
git_remote_get-0.3.1.dist-info/LICENSE
git_remote_get-0.3.1.dist-info/METADATA
git_remote_get-0.3.1.dist-info/WHEEL
git_remote_get-0.3.1.dist-info/entry_points.txt
git_remote_get-0.3.1.dist-info/RECORD
